transub/__init__.py
transub/__main__.py
transub/audio.py
transub/cli.py
transub/concurrent_translate.py
transub/config.py
transub/logger.py
transub/smart_retry.py
transub/state.py
transub/subtitles.py
transub/transcribe.py
transub/translate.py
transub/transub-sample.conf
transub-0.2.2.dist-info/licenses/LICENSE
transub-0.2.2.dist-info/METADATA
transub-0.2.2.dist-info/WHEEL
transub-0.2.2.dist-info/entry_points.txt
transub-0.2.2.dist-info/top_level.txt
transub-0.2.2.dist-info/RECORD
