Metadata-Version: 2.4
Name: transub
Version: 0.2.2
Summary: CLI tool to transcribe and translate subtitles from videos
Author: PiktCai
License-Expression: MIT
Project-URL: Homepage, https://github.com/PiktCai/transub
Project-URL: Repository, https://github.com/PiktCai/transub
Project-URL: Issues, https://github.com/PiktCai/transub/issues
Keywords: subtitles,transcription,translation,whisper,cli
Classifier: Development Status :: 3 - Alpha
Classifier: Environment :: Console
Classifier: Intended Audience :: End Users/Desktop
Classifier: Intended Audience :: Developers
Classifier: Programming Language :: Python
Classifier: Programming Language :: Python :: 3
Classifier: Programming Language :: Python :: 3.10
Classifier: Programming Language :: Python :: 3.11
Classifier: Programming Language :: Python :: 3.12
Classifier: Topic :: Multimedia :: Sound/Audio
Classifier: Topic :: Text Processing :: Linguistic
Classifier: Topic :: Utilities
Requires-Python: >=3.10
License-File: LICENSE
Requires-Dist: typer>=0.9
Requires-Dist: rich>=13.7
Requires-Dist: tomli>=2.0.1; python_version < "3.11"
Requires-Dist: tomli-w>=1.0
Requires-Dist: pydantic>=2.7
Requires-Dist: requests>=2.31
Requires-Dist: huggingface-hub>=0.21
Requires-Dist: tqdm>=4.66
Dynamic: license-file
